{
  "info": {
    "face": "License Plate", 
    "size": "-128",
    "bold": "0",
    "italic": "0",
    "charset": "",
    "unicode": "1",
    "stretchH": "80",
    "smooth": "1",
    "aa": "2",
    "padding": "0,0,0,0",
    "spacing": "5,5",
    "outline": "0"
  },
  "common": {
    "lineHeight": "115",
    "base": "93",
    "scaleW": "4096",
    "scaleH": "2048",
    "pages": "1",
    "packed": "0",
    "alphaChnl": "1",
    "redChnl": "0",
    "greenChnl": "0",
    "blueChnl": "0"
  },
  "pages": [
    {
      "id": "0",
      "file": "output_0.png"
    }
  ],
  "chars": {
    "count": "27",
    "char": [
      {
        "id": "48", 
        "x": "3730",
        "y": "1377",
        "width": "180",
        "height": "609",
        "xoffset": "-185",
        "yoffset": "10",
        "xadvance": "220",
        "page": "0",
        "chnl": "15"
      },
      {
        "id": "49", 
        "x": "3530",
        "y": "1377",
        "width": "200",
        "height": "609",
        "xoffset": "-185",
        "yoffset": "10",
        "xadvance": "220",
        "page": "0",
        "chnl": "15"
      },
      {
        "id": "50", 
        "x": "3330",
        "y": "1377",
        "width": "200",
        "height": "609",
        "xoffset": "-185",
        "yoffset": "10",
        "xadvance": "220",
        "page": "0",
        "chnl": "15"
      },
      {
        "id": "51", 
        "x": "3130",
        "y": "1377",
        "width": "200",
        "height": "609",
        "xoffset": "-185",
        "yoffset": "10",
        "xadvance": "220",
        "page": "0",
        "chnl": "15"
      },
      {
        "id": "52", 
        "x": "2930",
        "y": "1377",
        "width": "200",
        "height": "609",
        "xoffset": "-185",
        "yoffset": "10",
        "xadvance": "220",
        "page": "0",
        "chnl": "15"
      },
      {
        "id": "53", 
        "x": "2730",
        "y": "1377",
        "width": "200",
        "height": "609",
        "xoffset": "-185",
        "yoffset": "10",
        "xadvance": "220",
        "page": "0",
        "chnl": "15"
      },
      {
        "id": "54", 
        "x": "2530",
        "y": "1377",
        "width": "200",
        "height": "609",
        "xoffset": "-185",
        "yoffset": "10",
        "xadvance": "220",
        "page": "0",
        "chnl": "15"
      },
      {
        "id": "55", 
        "x": "2330",
        "y": "1377",
        "width": "200",
        "height": "609",
        "xoffset": "-185",
        "yoffset": "10",
        "xadvance": "220",
        "page": "0",
        "chnl": "15"
      },
      {
        "id": "56",
        "x": "2130",
        "y": "1377",
        "width": "200",
        "height": "609",
        "xoffset": "-185",
        "yoffset": "10",
        "xadvance": "220",
        "page": "0",
        "chnl": "15"
      },
      {
        "id": "57", 
        "x": "1930",
        "y": "1377",
        "width": "200",
        "height": "609",
        "xoffset": "-185",
        "yoffset": "10",
        "xadvance": "220",
        "page": "0",
        "chnl": "15"
      },
      {
        "id": "65", 
        "x": "3730",
        "y": "45",
        "width": "200",
        "height": "659",
        "xoffset": "20",
        "yoffset": "0",
        "xadvance": "250",
        "page": "0",
        "chnl": "15"
      },
      {
        "id": "66", 
        "x": "3530",
        "y": "45",
        "width": "200",
        "height": "659",
        "xoffset": "20",
        "yoffset": "0",
        "xadvance": "250",
        "page": "0",
        "chnl": "15"
      },
      {
        "id": "68", 
        "x": "3130",
        "y": "45",
        "width": "200",
        "height": "659",
        "xoffset": "20",
        "yoffset": "0",
        "xadvance": "250",
        "page": "0",
        "chnl": "15"
      },
      {
        "id": "69", 
        "x": "2130",
        "y": "45",
        "width": "200",
        "height": "659",
        "xoffset": "20",
        "yoffset": "0",
        "xadvance": "250",
        "page": "0",
        "chnl": "15"
      },
      {
        "id": "71", 
        "x": "1930",
        "y": "45",
        "width": "200",
        "height": "659",
        "xoffset": "20",
        "yoffset": "0",
        "xadvance": "250",
        "page": "0",
        "chnl": "15"
      },
      {
        "id": "72", 
        "x": "2930",
        "y": "714",
        "width": "200",
        "height": "659",
        "xoffset": "20",
        "yoffset": "0",
        "xadvance": "250",
        "page": "0",
        "chnl": "15"
      },
      {
        "id": "74", 
        "x": "3330",
        "y": "45",
        "width": "200",
        "height": "659",
        "xoffset": "20",
        "yoffset": "0",
        "xadvance": "250",
        "page": "0",
        "chnl": "15"
      },
      {
        "id": "75", 
        "x": "3730",
        "y": "714",
        "width": "200",
        "height": "659",
        "xoffset": "20",
        "yoffset": "0",
        "xadvance": "250",
        "page": "0",
        "chnl": "15"
      },
      {
        "id": "76", 
        "x": "3530",
        "y": "714",
        "width": "200",
        "height": "659",
        "xoffset": "20",
        "yoffset": "0",
        "xadvance": "250",
        "page": "0",
        "chnl": "15"
      },
      {
        "id": "78", 
        "x": "3130",
        "y": "714",
        "width": "200",
        "height": "659",
        "xoffset": "20",
        "yoffset": "0",
        "xadvance": "250",
        "page": "0",
        "chnl": "15"
      },
      { 
        "id": "82", 
        "x": "2930",
        "y": "45",
        "width": "200",
        "height": "659",
        "xoffset": "20",
        "yoffset": "0",
        "xadvance": "250",
        "page": "0",
        "chnl": "15"
      },
      {
        "id": "83", 
        "x": "2730",
        "y": "45",
        "width": "200",
        "height": "659",
        "xoffset": "20",
        "yoffset": "0",
        "xadvance": "250",
        "page": "0",
        "chnl": "15"
      },
      {
        "id": "84", 
        "x": "2330",
        "y": "45",
        "width": "200",
        "height": "659",
        "xoffset": "20",
        "yoffset": "0",
        "xadvance": "250",
        "page": "0",
        "chnl": "15"
      },
      {
        "id": "85",
        "x": "2730",
        "y": "714",
        "width": "200",
        "height": "659",
        "xoffset": "20",
        "yoffset": "0",
        "xadvance": "250",
        "page": "0",
        "chnl": "15"
      },
      {
        "id": "86", 
        "x": "2530",
        "y": "714",
        "width": "200",
        "height": "659",
        "xoffset": "20",
        "yoffset": "0",
        "xadvance": "250",
        "page": "0",
        "chnl": "15"
      },
      {
        "id": "88", 
        "x": "2530",
        "y": "45",
        "width": "200",
        "height": "659",
        "xoffset": "20",
        "yoffset": "0",
        "xadvance": "250",
        "page": "0",
        "chnl": "15"
      },
      {
        "id": "90",
        "x": "3330",
        "y": "714",
        "width": "200",
        "height": "659",
        "xoffset": "20",
        "yoffset": "0",
        "xadvance": "250",
        "page": "0",
        "chnl": "15"
      }
    ]
  }
}